logic/__init__.py
logic_toolchain-0.0.2.dist-info/LICENSE
logic_toolchain-0.0.2.dist-info/METADATA
logic_toolchain-0.0.2.dist-info/WHEEL
logic_toolchain-0.0.2.dist-info/top_level.txt
logic_toolchain-0.0.2.dist-info/RECORD
